main.py
robospeaker_win-0.1.7.dist-info/METADATA
robospeaker_win-0.1.7.dist-info/WHEEL
robospeaker_win-0.1.7.dist-info/entry_points.txt
robospeaker_win-0.1.7.dist-info/top_level.txt
robospeaker_win-0.1.7.dist-info/RECORD
