Metadata-Version: 2.4
Name: robospeaker-win
Version: 0.1.7
Summary: A simple, lightweight Text-to-Speech (TTS) tool for Windows using SAPI.
Author: Mahir29Flame
License: MIT
Project-URL: Homepage, https://github.com/Mahir29Flame/RoboSpeaker
Project-URL: Repository, https://github.com/Mahir29Flame/RoboSpeaker.git
Keywords: tts,speech,windows,sapi,robospeaker
Classifier: Development Status :: 4 - Beta
Classifier: Intended Audience :: Developers
Classifier: License :: OSI Approved :: MIT License
Classifier: Operating System :: Microsoft :: Windows
Classifier: Programming Language :: Python :: 3
Requires-Python: >=3.11
Requires-Dist: pywin32>=306
Requires-Dist: rich>=13.0.0
